contract_wasm_interface_parser/__init__.py
contract_wasm_interface_parser-0.2.0.dist-info/LICENSE
contract_wasm_interface_parser-0.2.0.dist-info/METADATA
contract_wasm_interface_parser-0.2.0.dist-info/WHEEL
contract_wasm_interface_parser-0.2.0.dist-info/RECORD
