Metadata-Version: 2.1
Name: contract-wasm-interface-parser
Version: 0.2.0
Summary: Contract interface metadata parser for binary Stellar WASM
License: Apache-2.0
Author: overcat
Author-email: 4catcode@gmail.com
Requires-Python: >=3.8,<4.0
Classifier: License :: OSI Approved :: Apache Software License
Classifier: Programming Language :: Python :: 3
Classifier: Programming Language :: Python :: 3.8
Classifier: Programming Language :: Python :: 3.9
Classifier: Programming Language :: Python :: 3.10
Classifier: Programming Language :: Python :: 3.11
Classifier: Programming Language :: Python :: 3.12
Requires-Dist: stellar-sdk (>=10.0.0,<11.0.0)
